{"countries": [{"athletes": [{"discipline": "AS", "firstName": "Mireia", "gender": "W", "age": 21, "cityOfResidence": "Ad500 Andorra la Vella", "weightKG": 60, "heightCM": 162, "dateOfBirth": "1988/10/09", "countryOfResidenceId": "AND", "linkFR": "/fr/ski-alpine-olympique/athl\u00e8tes/mireia-gutierrez_ath1000402kg.html", "lastName": "Gutierrez", "id": "1000402", "link": "/olympic-alpine-skiing/athletes/mireia-gutierrez_ath1000402rJ.html", "noc": "AND", "events": {"ASW040000": "NONE", "ASW105000": "NONE", "ASW020000": "NONE", "ASW030000": "NONE", "ASW010000": "NONE"}, "cityOfBirth": "Andorra", "countryOfBirthId": "AND"}, {"discipline": "AS", "firstName": "Sofie", "gender": "W", "age": 18, "cityOfResidence": "Andorra la Vella", "weightKG": 70, "heightCM": 172, "dateOfBirth": "1991/04/09", "countryOfResidenceId": "AND", "linkFR": "/fr/ski-alpine-olympique/athl\u00e8tes/sofie-juarez_ath1015020OZ.html", "lastName": "Juarez", "id": "1015020", "link": "/olympic-alpine-skiing/athletes/sofie-juarez_ath1015020AG.html", "noc": "AND", "events": {"ASW020000": "NONE", "ASW030000": "NONE"}, "cityOfBirth": "Incles", "countryOfBirthId": "AND"}], "noc": "AND"}, {"athletes": [{"discipline": "AS", "firstName": "Nicol", "gender": "W", "age": 19, "cityOfResidence": "San Carlos de Bariloche", "weightKG": 62, "heightCM": 167, "dateOfBirth": "1990/02/16", "countryOfResidenceId": "ARG", "linkFR": "/fr/ski-alpine-olympique/athl\u00e8tes/nicol-gastaldi_ath1016785vv.html", "lastName": "Gastaldi", "id": "1016785", "link": "/olympic-alpine-skiing/athletes/nicol-gastaldi_ath1016785sA.html", "noc": "ARG", "events": {"ASW020000": "NONE", "ASW030000": "NONE"}, "cityOfBirth": "Piove di Sacco", "countryOfBirthId": "ITA"}, {"discipline": "AS", "firstName": "Macarena", "gender": "W", "age": 25, "cityOfResidence": "San Carlos de Bariloche", "weightKG": 62, "heightCM": 167, "dateOfBirth": "1984/11/22", "countryOfResidenceId": "ARG", "linkFR": "/fr/ski-alpine-olympique/athl\u00e8tes/macarena-simari-birkner_ath1014577IR.html", "lastName": "Simari Birkner", "id": "1014577", "link": "/olympic-alpine-skiing/athletes/macarena-simari-birkner_ath1014577za.html", "noc": "ARG", "events": {"ASW040000": "NONE", "ASW105000": "NONE", "ASW020000": "NONE", "ASW030000": "NONE", "ASW010000": "NONE"}, "cityOfBirth": "San Carlos de Bariloche", "countryOfBirthId": "ARG"}, {"discipline": "AS", "firstName": "Maria Belen", "gender": "W", "age": 27, "cityOfResidence": "San Carlos de Bariloche", "weightKG": 60, "heightCM": 165, "dateOfBirth": "1982/08/18", "countryOfResidenceId": "ARG", "linkFR": "/fr/ski-alpine-olympique/athl\u00e8tes/maria-belen-simari-birkner_ath1014567tB.html", "lastName": "Simari Birkner", "id": "1014567", "link": "/olympic-alpine-skiing/athletes/maria-belen-simari-birkner_ath1014567zu.html", "noc": "ARG", "events": {"ASW040000": "NONE", "ASW105000": "NONE", "ASW020000": "NONE", "ASW030000": "NONE", "ASW010000": "NONE"}, "cityOfBirth": "San Carlos de Bariloche", "countryOfBirthId": "ARG"}], "noc": "ARG"}, {"athletes": [{"discipline": "AS", "firstName": "Ani-Matilda", "gender": "W", "age": 21, "cityOfResidence": "Novato", "weightKG": 68, "heightCM": 163, "dateOfBirth": "1989/02/07", "countryOfResidenceId": "USA", "linkFR": "/fr/ski-alpine-olympique/athl\u00e8tes/ani-matilda-serebrakian_ath200289AO.html", "lastName": "Serebrakian", "id": "200289", "link": "/olympic-alpine-skiing/athletes/ani-matilda-serebrakian_ath200289mL.html", "noc": "ARM", "events": {"ASW020000": "NONE", "ASW030000": "NONE"}, "cityOfBirth": "los Angeles", "countryOfBirthId": "USA"}], "noc": "ARM"}, {"athletes": [{"discipline": "AS", "firstName": "Anna", "gender": "W", "age": 20, "cityOfResidence": "Adnet", "weightKG": 64, "heightCM": 166, "dateOfBirth": "1989/06/18", "countryOfResidenceId": "AUT", "linkFR": "/fr/ski-alpine-olympique/athl\u00e8tes/anna-fenninger_ath1029857kL.html", "lastName": "Fenninger", "id": "1029857", "link": "/olympic-alpine-skiing/athletes/anna-fenninger_ath1029857gQ.html", "noc": "AUT", "events": {"ASW105000": "NONE", "ASW020000": "NONE", "ASW010000": "NONE"}, "cityOfBirth": "Hallein", "countryOfBirthId": "AUT"}, {"discipline": "AS", "firstName": "Michaela", "gender": "W", "age": 24, "cityOfResidence": "Filzmoos", "weightKG": 64, "heightCM": 168, "dateOfBirth": "1985/03/18", "countryOfResidenceId": "AUT", "linkFR": "/fr/ski-alpine-olympique/athl\u00e8tes/michaela-kirchgasser_ath1029939Sk.html", "lastName": "Kirchgasser", "id": "1029939", "link": "/olympic-alpine-skiing/athletes/michaela-kirchgasser_ath1029939uJ.html", "noc": "AUT", "events": {"ASW105000": "NONE", "ASW020000": "NONE", "ASW010000": "NONE"}, "cityOfBirth": "Schwarzach", "countryOfBirthId": "AUT"}, {"discipline": "AS", "firstName": "Marlies", "gender": "W", "age": 28, "cityOfResidence": "Saalfelden", "weightKG": 66, "heightCM": 172, "dateOfBirth": "1981/05/31", "countryOfResidenceId": "AUT", "linkFR": "/fr/ski-alpine-olympique/athl\u00e8tes/marlies-schild_ath1030153jG.html", "lastName": "Schild", "id": "1030153", "link": "/olympic-alpine-skiing/athletes/marlies-schild_ath1030153fL.html", "noc": "AUT", "events": {"ASW020000": "NONE", "ASW030000": "NONE"}, "cityOfBirth": "Admont", "countryOfBirthId": "AUT"}, {"discipline": "AS", "firstName": "Kathrin", "gender": "W", "age": 23, "cityOfResidence": "Goestling A D Ybbs", "weightKG": 63, "heightCM": 167, "dateOfBirth": "1986/08/05", "countryOfResidenceId": "AUT", "linkFR": "/fr/ski-alpine-olympique/athl\u00e8tes/kathrin-zettel_ath1030219QK.html", "lastName": "Zettel", "id": "1030219", "link": "/olympic-alpine-skiing/athletes/kathrin-zettel_ath1030219MP.html", "noc": "AUT", "events": {"ASW105000": "NONE", "ASW020000": "NONE", "ASW030000": "NONE", "ASW010000": "NONE"}, "cityOfBirth": "Scheibbs", "countryOfBirthId": "AUT"}], "noc": "AUT"}, {"athletes": [{"discipline": "AS", "firstName": "Gaia", "gender": "W", "age": 31, "cityOfResidence": "Baku", "weightKG": 60, "heightCM": 167, "dateOfBirth": "1978/07/08", "countryOfResidenceId": "AZE", "linkFR": "/fr/ski-alpine-olympique/athl\u00e8tes/gaia-bassani-antivari_ath1012571gg.html", "lastName": "Bassani Antivari", "id": "1012571", "link": "/olympic-alpine-skiing/athletes/gaia-bassani-antivari_ath1012571NR.html", "noc": "AZE", "events": {"ASW020000": "NONE", "ASW030000": "NONE"}, "cityOfBirth": "Milan", "countryOfBirthId": "ITA"}], "noc": "AZE"}, {"athletes": [{"discipline": "AS", "firstName": "Karen", "gender": "W", "age": 26, "cityOfResidence": "Boirs", "weightKG": 71, "heightCM": 173, "dateOfBirth": "1983/03/31", "countryOfResidenceId": "BEL", "linkFR": "/fr/ski-alpine-olympique/athl\u00e8tes/karen-persyn_ath1033249ih.html", "lastName": "Persyn", "id": "1033249", "link": "/olympic-alpine-skiing/athletes/karen-persyn_ath1033249UO.html", "noc": "BEL", "events": {"ASW020000": "NONE"}, "cityOfBirth": "Rumst", "countryOfBirthId": "BEL"}], "noc": "BEL"}, {"athletes": [{"discipline": "AS", "firstName": "Maja", "gender": "W", "age": 21, "cityOfResidence": "Sarajevo", "weightKG": 67, "heightCM": 172, "dateOfBirth": "1988/05/23", "countryOfResidenceId": "BIH", "linkFR": "/fr/ski-alpine-olympique/athl\u00e8tes/maja-klepic_ath1033957jC.html", "lastName": "Klepic", "id": "1033957", "link": "/olympic-alpine-skiing/athletes/maja-klepic_ath1033957PX.html", "noc": "BIH", "events": {"ASW020000": "NONE", "ASW030000": "NONE"}, "cityOfBirth": "Sarajevo", "countryOfBirthId": "BIH"}, {"discipline": "AS", "firstName": "Zana", "gender": "W", "age": 24, "cityOfResidence": "Sarajevo", "weightKG": 58, "heightCM": 164, "dateOfBirth": "1985/06/24", "countryOfResidenceId": "BIH", "linkFR": "/fr/ski-alpine-olympique/athl\u00e8tes/zana-novakovic_ath1033949Hs.html", "lastName": "Novakovic", "id": "1033949", "link": "/olympic-alpine-skiing/athletes/zana-novakovic_ath1033949Dx.html", "noc": "BIH", "events": {"ASW040000": "NONE", "ASW020000": "NONE", "ASW030000": "NONE"}, "cityOfBirth": "Sarajevo", "countryOfBirthId": "BIH"}], "noc": "BIH"}, {"athletes": [{"discipline": "AS", "firstName": "Lizaveta", "gender": "W", "age": 22, "cityOfResidence": "Minsk", "weightKG": 62, "heightCM": 168, "dateOfBirth": "1987/04/18", "countryOfResidenceId": "BLR", "linkFR": "/fr/ski-alpine-olympique/athl\u00e8tes/lizaveta-kuzmenka_ath1015105ck.html", "lastName": "Kuzmenka", "id": "1015105", "link": "/olympic-alpine-skiing/athletes/lizaveta-kuzmenka_ath1015105oZ.html", "noc": "BLR", "events": {"ASW040000": "NONE", "ASW105000": "NONE", "ASW020000": "NONE", "ASW030000": "NONE"}, "cityOfBirth": "St.petersburg", "countryOfBirthId": "RUS"}, {"discipline": "AS", "firstName": "Maria", "gender": "W", "age": 20, "cityOfResidence": "Minsk", "weightKG": 66, "heightCM": 166, "dateOfBirth": "1989/10/18", "countryOfResidenceId": "BLR", "linkFR": "/fr/ski-alpine-olympique/athl\u00e8tes/maria-shkanova_ath1015111MA.html", "lastName": "Shkanova", "id": "1015111", "link": "/olympic-alpine-skiing/athletes/maria-shkanova_ath1015111IF.html", "noc": "BLR", "events": {"ASW040000": "NONE", "ASW105000": "NONE", "ASW020000": "NONE", "ASW030000": "NONE"}, "cityOfBirth": "St.petersburg", "countryOfBirthId": "RUS"}], "noc": "BLR"}, {"athletes": [{"discipline": "AS", "firstName": "Maya", "gender": "W", "age": 17, "cityOfResidence": "Geneva", "weightKG": 53, "heightCM": 161, "dateOfBirth": "1992/03/03", "countryOfResidenceId": "SUI", "linkFR": "/fr/ski-alpine-olympique/athl\u00e8tes/maya-harrisson_ath1006000TN.html", "lastName": "Harrisson", "id": "1006000", "link": "/olympic-alpine-skiing/athletes/maya-harrisson_ath1006000PS.html", "noc": "BRA", "events": {"ASW020000": "NONE", "ASW030000": "NONE"}, "cityOfBirth": "Duas Barras", "countryOfBirthId": "BRA"}], "noc": "BRA"}, {"athletes": [{"discipline": "AS", "firstName": "Maria", "gender": "W", "age": 24, "cityOfResidence": "Sofia", "weightKG": 65, "heightCM": 165, "dateOfBirth": "1986/01/02", "countryOfResidenceId": "BUL", "linkFR": "/fr/ski-alpine-olympique/athl\u00e8tes/maria-kirkova_ath1015765Wj.html", "lastName": "Kirkova", "id": "1015765", "link": "/olympic-alpine-skiing/athletes/maria-kirkova_ath1015765Nc.html", "noc": "BUL", "events": {"ASW040000": "NONE", "ASW105000": "NONE", "ASW020000": "NONE", "ASW030000": "NONE", "ASW010000": "NONE"}, "cityOfBirth": "Sofia", "countryOfBirthId": "BUL"}], "noc": "BUL"}, {"athletes": [{"discipline": "AS", "firstName": "Brigitte", "gender": "W", "age": 24, "cityOfResidence": "Sault Ste Marie", "weightKG": 63, "heightCM": 167, "dateOfBirth": "1985/11/30", "countryOfResidenceId": "CAN", "linkFR": "/fr/ski-alpine-olympique/athl\u00e8tes/brigitte-acton_ath1009871mC.html", "lastName": "Acton", "id": "1009871", "link": "/olympic-alpine-skiing/athletes/brigitte-acton_ath1009871iH.html", "noc": "CAN", "events": {"ASW020000": "NONE", "ASW030000": "NONE"}, "cityOfBirth": "Sault Ste Marie", "countryOfBirthId": "CAN"}, {"discipline": "AS", "firstName": "Marie-Michele", "gender": "W", "age": 20, "cityOfResidence": "Lac-Etchemin", "weightKG": 67, "heightCM": 177, "dateOfBirth": "1989/04/25", "countryOfResidenceId": "CAN", "linkFR": "/fr/ski-alpine-olympique/athl\u00e8tes/marie-michele-gagnon_ath1009874zO.html", "lastName": "Gagnon", "id": "1009874", "link": "/olympic-alpine-skiing/athletes/marie-michele-gagnon_ath1009874an.html", "noc": "CAN", "events": {"ASW020000": "NONE", "ASW030000": "NONE"}, "cityOfBirth": "Levis", "countryOfBirthId": "CAN"}, {"discipline": "AS", "firstName": "Anna", "gender": "W", "age": 24, "cityOfResidence": "Mont Tremblant", "weightKG": 75, "heightCM": 178, "dateOfBirth": "1986/01/23", "countryOfResidenceId": "CAN", "linkFR": "/fr/ski-alpine-olympique/athl\u00e8tes/anna-goodman_ath1030459SC.html", "lastName": "Goodman", "id": "1030459", "link": "/olympic-alpine-skiing/athletes/anna-goodman_ath1030459Dj.html", "noc": "CAN", "events": {"ASW020000": "NONE"}, "cityOfBirth": "Montreal", "countryOfBirthId": "CAN"}, {"discipline": "AS", "firstName": "Erin", "gender": "W", "age": 19, "cityOfResidence": "Guelph", "weightKG": 65, "heightCM": 169, "dateOfBirth": "1990/05/25", "countryOfResidenceId": "CAN", "linkFR": "/fr/ski-alpine-olympique/athl\u00e8tes/erin-mielzynski_ath1046792AL.html", "lastName": "Mielzynski", "id": "1046792", "link": "/olympic-alpine-skiing/athletes/erin-mielzynski_ath1046792Bc.html", "noc": "CAN", "events": {"ASW105000": "NONE", "ASW020000": "NONE"}, "cityOfBirth": "Brampton", "countryOfBirthId": "CAN"}], "noc": "CAN"}, {"athletes": [{"discipline": "AS", "firstName": "Noelle", "gender": "W", "age": 19, "cityOfResidence": "Santiago", "weightKG": 75, "heightCM": 173, "dateOfBirth": "1990/11/30", "countryOfResidenceId": "CHI", "linkFR": "/fr/ski-alpine-olympique/athl\u00e8tes/noelle-barahona_ath1006557vo.html", "lastName": "Barahona", "id": "1006557", "link": "/olympic-alpine-skiing/athletes/noelle-barahona_ath1006557xF.html", "noc": "CHI", "events": {"ASW040000": "NONE", "ASW105000": "NONE", "ASW020000": "NONE", "ASW030000": "NONE", "ASW010000": "NONE"}, "cityOfBirth": "Santiago", "countryOfBirthId": "CHI"}], "noc": "CHI"}, {"athletes": [{"discipline": "AS", "firstName": "Lina", "gender": "W", "age": 22, "cityOfResidence": "Beijing", "weightKG": 60, "heightCM": 160, "dateOfBirth": "1987/10/26", "countryOfResidenceId": "CHN", "linkFR": "/fr/ski-alpine-olympique/athl\u00e8tes/lina-xia_ath1023497XF.html", "lastName": "Xia", "id": "1023497", "link": "/olympic-alpine-skiing/athletes/lina-xia_ath1023497kG.html", "noc": "CHN", "events": {"ASW020000": "NONE", "ASW030000": "NONE"}, "cityOfBirth": "Harbin", "countryOfBirthId": "CHN"}], "noc": "CHN"}, {"athletes": [{"discipline": "AS", "firstName": "Cynthia", "gender": "W", "age": 26, "cityOfResidence": "Gryon", "weightKG": 52, "heightCM": 161, "dateOfBirth": "1983/05/12", "countryOfResidenceId": "SUI", "linkFR": "/fr/ski-alpine-olympique/athl\u00e8tes/cynthia-denzler_ath1056710zt.html", "lastName": "Denzler", "id": "1056710", "link": "/olympic-alpine-skiing/athletes/cynthia-denzler_ath1056710BK.html", "noc": "COL", "events": {"ASW020000": "NONE", "ASW030000": "NONE"}, "cityOfBirth": "Santa Ana", "countryOfBirthId": "USA"}], "noc": "COL"}, {"athletes": [{"discipline": "AS", "firstName": "Matea", "gender": "W", "age": 22, "cityOfResidence": "Rijeka", "weightKG": 59, "heightCM": 165, "dateOfBirth": "1987/06/08", "countryOfResidenceId": "CRO", "linkFR": "/fr/ski-alpine-olympique/athl\u00e8tes/matea-ferk_ath1006302st.html", "lastName": "Ferk", "id": "1006302", "link": "/olympic-alpine-skiing/athletes/matea-ferk_ath1006302UC.html", "noc": "CRO", "events": {"ASW020000": "NONE", "ASW030000": "NONE"}, "cityOfBirth": "Rijeka", "countryOfBirthId": "CRO"}, {"discipline": "AS", "firstName": "Nika", "gender": "W", "age": 25, "cityOfResidence": "Samobor", "weightKG": 68, "heightCM": 167, "dateOfBirth": "1984/12/14", "countryOfResidenceId": "CRO", "linkFR": "/fr/ski-alpine-olympique/athl\u00e8tes/nika-fleiss_ath1006301bJ.html", "lastName": "Fleiss", "id": "1006301", "link": "/olympic-alpine-skiing/athletes/nika-fleiss_ath1006301He.html", "noc": "CRO", "events": {"ASW020000": "NONE", "ASW030000": "NONE"}, "cityOfBirth": "Brezice", "countryOfBirthId": "SLO"}, {"discipline": "AS", "firstName": "Ana", "gender": "W", "age": 23, "cityOfResidence": "Rijeka", "weightKG": 60, "heightCM": 166, "dateOfBirth": "1986/12/28", "countryOfResidenceId": "CRO", "linkFR": "/fr/ski-alpine-olympique/athl\u00e8tes/ana-jelusic_ath1006300ru.html", "lastName": "Jelusic", "id": "1006300", "link": "/olympic-alpine-skiing/athletes/ana-jelusic_ath1006300YP.html", "noc": "CRO", "events": {"ASW020000": "NONE", "ASW030000": "NONE"}, "cityOfBirth": "Rijeka", "countryOfBirthId": "CRO"}, {"discipline": "AS", "firstName": "Sofija", "gender": "W", "age": 20, "cityOfResidence": "Zagreb", "weightKG": 69, "heightCM": 166, "dateOfBirth": "1990/01/18", "countryOfResidenceId": "CRO", "linkFR": "/fr/ski-alpine-olympique/athl\u00e8tes/sofija-novoselic_ath1006303GE.html", "lastName": "Novoselic", "id": "1006303", "link": "/olympic-alpine-skiing/athletes/sofija-novoselic_ath1006303Mh.html", "noc": "CRO", "events": {"ASW020000": "NONE"}, "cityOfBirth": "Zagreb", "countryOfBirthId": "CRO"}], "noc": "CRO"}, {"athletes": [{"discipline": "AS", "firstName": "Sophia", "gender": "W", "age": 19, "cityOfResidence": "Nicosia", "weightKG": 56, "heightCM": 160, "dateOfBirth": "1990/04/05", "countryOfResidenceId": "CYP", "linkFR": "/fr/ski-alpine-olympique/athl\u00e8tes/sophia-papamichalopoulou_ath1006776Yj.html", "lastName": "Papamichalopoulou", "id": "1006776", "link": "/olympic-alpine-skiing/athletes/sophia-papamichalopoulou_ath1006776VE.html", "noc": "CYP", "events": {"ASW020000": "NONE", "ASW030000": "NONE"}, "cityOfBirth": "Athens", "countryOfBirthId": "GRE"}], "noc": "CYP"}, {"athletes": [{"discipline": "AS", "firstName": "Klara", "gender": "W", "age": 20, "cityOfResidence": "Zlin", "weightKG": 77, "heightCM": 179, "dateOfBirth": "1989/07/13", "countryOfResidenceId": "CZE", "linkFR": "/fr/ski-alpine-olympique/athl\u00e8tes/klara-krizova_ath1024925Qp.html", "lastName": "Krizova", "id": "1024925", "link": "/olympic-alpine-skiing/athletes/klara-krizova_ath1024925Hi.html", "noc": "CZE", "events": {"ASW040000": "NONE", "ASW105000": "NONE", "ASW020000": "NONE", "ASW030000": "NONE", "ASW010000": "NONE"}, "cityOfBirth": "Zlin", "countryOfBirthId": "CZE"}, {"discipline": "AS", "firstName": "Sarka", "gender": "W", "age": 25, "cityOfResidence": "Praha 10", "weightKG": 70, "heightCM": 175, "dateOfBirth": "1985/02/11", "countryOfResidenceId": "CZE", "linkFR": "/fr/ski-alpine-olympique/athl\u00e8tes/sarka-zahrobska_ath1024932Tx.html", "lastName": "Zahrobska", "id": "1024932", "link": "/olympic-alpine-skiing/athletes/sarka-zahrobska_ath1024932VO.html", "noc": "CZE", "events": {"ASW040000": "NONE", "ASW105000": "NONE", "ASW020000": "NONE", "ASW030000": "NONE", "ASW010000": "NONE"}, "cityOfBirth": "Benecko", "countryOfBirthId": "CZE"}, {"discipline": "AS", "firstName": "Petra", "gender": "W", "age": 31, "cityOfResidence": "Liberec", "weightKG": 68, "heightCM": 170, "dateOfBirth": "1978/09/05", "countryOfResidenceId": "CZE", "linkFR": "/fr/ski-alpine-olympique/athl\u00e8tes/petra-zakourilova_ath1024930eP.html", "lastName": "Zakourilova", "id": "1024930", "link": "/olympic-alpine-skiing/athletes/petra-zakourilova_ath1024930qE.html", "noc": "CZE", "events": {"ASW020000": "NONE", "ASW030000": "NONE"}, "cityOfBirth": "Liberec", "countryOfBirthId": "CZE"}], "noc": "CZE"}, {"athletes": [{"discipline": "AS", "firstName": "Yina", "gender": "W", "age": 16, "cityOfResidence": "98075", "weightKG": 55, "heightCM": 156, "dateOfBirth": "1993/05/22", "countryOfResidenceId": "USA", "linkFR": "/fr/ski-alpine-olympique/athl\u00e8tes/yina-moe-lange_ath1017709YA.html", "lastName": "Moe-Lange", "id": "1017709", "link": "/olympic-alpine-skiing/athletes/yina-moe-lange_ath1017709UF.html", "noc": "DEN", "events": {"ASW020000": "NONE", "ASW030000": "NONE"}, "cityOfBirth": "Tokyo", "countryOfBirthId": "JPN"}], "noc": "DEN"}, {"athletes": [{"discipline": "AS", "firstName": "Andrea", "gender": "W", "age": 19, "cityOfResidence": "Comarruga", "weightKG": 56, "heightCM": 168, "dateOfBirth": "1990/03/13", "countryOfResidenceId": "ESP", "linkFR": "/fr/ski-alpine-olympique/athl\u00e8tes/andrea-jardi_ath1015359Za.html", "lastName": "Jardi", "id": "1015359", "link": "/olympic-alpine-skiing/athletes/andrea-jardi_ath1015359LH.html", "noc": "ESP", "events": {"ASW040000": "NONE", "ASW105000": "NONE", "ASW020000": "NONE", "ASW030000": "NONE"}, "cityOfBirth": "Tarragona", "countryOfBirthId": "ESP"}], "noc": "ESP"}, {"athletes": [{"discipline": "AS", "firstName": "Tiiu", "gender": "W", "age": 28, "cityOfResidence": "Tallinn", "weightKG": 59, "heightCM": 160, "dateOfBirth": "1982/01/05", "countryOfResidenceId": "EST", "linkFR": "/fr/ski-alpine-olympique/athl\u00e8tes/tiiu-nurmberg_ath1017391ms.html", "lastName": "Nurmberg", "id": "1017391", "link": "/olympic-alpine-skiing/athletes/tiiu-nurmberg_ath1017391dl.html", "noc": "EST", "events": {"ASW020000": "NONE", "ASW030000": "NONE"}, "cityOfBirth": "Montreal", "countryOfBirthId": "CAN"}], "noc": "EST"}, {"athletes": [{"discipline": "AS", "firstName": "Sanni", "gender": "W", "age": 20, "cityOfResidence": "Ylojarvi", "weightKG": 58, "heightCM": 165, "dateOfBirth": "1989/11/08", "countryOfResidenceId": "FIN", "linkFR": "/fr/ski-alpine-olympique/athl\u00e8tes/sanni-leinonen_ath1018299oQ.html", "lastName": "Leinonen", "id": "1018299", "link": "/olympic-alpine-skiing/athletes/sanni-leinonen_ath1018299kV.html", "noc": "FIN", "events": {"ASW040000": "NONE", "ASW105000": "NONE", "ASW020000": "NONE", "ASW030000": "NONE"}, "cityOfBirth": "Siilinjarvi", "countryOfBirthId": "FIN"}, {"discipline": "AS", "firstName": "Tanja", "gender": "W", "age": 29, "cityOfResidence": "Rovaniemi", "weightKG": 67, "heightCM": 170, "dateOfBirth": "1980/04/06", "countryOfResidenceId": "FIN", "linkFR": "/fr/ski-alpine-olympique/athl\u00e8tes/tanja-poutiainen_ath1018300hU.html", "lastName": "Poutiainen", "id": "1018300", "link": "/olympic-alpine-skiing/athletes/tanja-poutiainen_ath1018300nx.html", "noc": "FIN", "events": {"ASW040000": "NONE", "ASW105000": "NONE", "ASW020000": "NONE", "ASW030000": "NONE"}, "cityOfBirth": "Rovaniemi", "countryOfBirthId": "FIN"}], "noc": "FIN"}, {"athletes": [{"discipline": "AS", "firstName": "Sandrine", "gender": "W", "age": 27, "cityOfResidence": "Naves Parmelan", "weightKG": 66, "heightCM": 181, "dateOfBirth": "1982/10/06", "countryOfResidenceId": "FRA", "linkFR": "/fr/ski-alpine-olympique/athl\u00e8tes/sandrine-aubert_ath1031047IY.html", "lastName": "Aubert", "id": "1031047", "link": "/olympic-alpine-skiing/athletes/sandrine-aubert_ath1031047Jp.html", "noc": "FRA", "events": {"ASW105000": "NONE", "ASW020000": "NONE", "ASW010000": "NONE"}, "cityOfBirth": "Echirolles", "countryOfBirthId": "FRA"}, {"discipline": "AS", "firstName": "Anne-Sophie", "gender": "W", "age": 21, "cityOfResidence": "Courchevel", "weightKG": 70, "heightCM": 170, "dateOfBirth": "1988/02/23", "countryOfResidenceId": "FRA", "linkFR": "/fr/ski-alpine-olympique/athl\u00e8tes/anne-sophie-barthet_ath1031050jQ.html", "lastName": "Barthet", "id": "1031050", "link": "/olympic-alpine-skiing/athletes/anne-sophie-barthet_ath1031050Bt.html", "noc": "FRA", "events": {"ASW020000": "NONE"}, "cityOfBirth": "Toulouse", "countryOfBirthId": "FRA"}, {"discipline": "AS", "firstName": "Claire", "gender": "W", "age": 27, "cityOfResidence": "Lanslebourg", "weightKG": 70, "heightCM": 164, "dateOfBirth": "1982/09/05", "countryOfResidenceId": "FRA", "linkFR": "/fr/ski-alpine-olympique/athl\u00e8tes/claire-dautherives_ath1031056tB.html", "lastName": "Dautherives", "id": "1031056", "link": "/olympic-alpine-skiing/athletes/claire-dautherives_ath1031056KC.html", "noc": "FRA", "events": {"ASW020000": "NONE"}, "cityOfBirth": "St Jean de Maurienne", "countryOfBirthId": "FRA"}, {"discipline": "AS", "firstName": "Nastasia", "gender": "W", "age": 21, "cityOfResidence": "Nice", "weightKG": 65, "heightCM": 177, "dateOfBirth": "1988/09/12", "countryOfResidenceId": "FRA", "linkFR": "/fr/ski-alpine-olympique/athl\u00e8tes/nastasia-noens_ath1031067pG.html", "lastName": "Noens", "id": "1031067", "link": "/olympic-alpine-skiing/athletes/nastasia-noens_ath1031067lL.html", "noc": "FRA", "events": {"ASW020000": "NONE"}, "cityOfBirth": "Nice", "countryOfBirthId": "FRA"}], "noc": "FRA"}, {"athletes": [{"discipline": "AS", "firstName": "Chemmy", "gender": "W", "age": 27, "cityOfResidence": "East Moseley", "weightKG": 70, "heightCM": 170, "dateOfBirth": "1982/07/10", "countryOfResidenceId": "GBR", "linkFR": "/fr/ski-alpine-olympique/athl\u00e8tes/chemmy-alcott_ath1020714kq.html", "lastName": "Alcott", "id": "1020714", "link": "/olympic-alpine-skiing/athletes/chemmy-alcott_ath1020714bj.html", "noc": "GBR", "events": {"ASW040000": "NONE", "ASW105000": "NONE", "ASW020000": "NONE", "ASW030000": "NONE", "ASW010000": "NONE"}, "cityOfBirth": "London", "countryOfBirthId": "GBR"}], "noc": "GBR"}, {"athletes": [{"discipline": "AS", "firstName": "Nino", "gender": "W", "age": 16, "cityOfResidence": "Tbilisi", "weightKG": 60, "heightCM": 168, "dateOfBirth": "1993/07/01", "countryOfResidenceId": "GEO", "linkFR": "/fr/ski-alpine-olympique/athl\u00e8tes/nino-tsiklauri_ath1006367mc.html", "lastName": "Tsiklauri", "id": "1006367", "link": "/olympic-alpine-skiing/athletes/nino-tsiklauri_ath1006367ih.html", "noc": "GEO", "events": {"ASW020000": "NONE", "ASW030000": "NONE"}, "cityOfBirth": "Tbilisi", "countryOfBirthId": "GEO"}], "noc": "GEO"}, {"athletes": [{"discipline": "AS", "firstName": "Katharina", "gender": "W", "age": 20, "cityOfResidence": "Germering", "weightKG": 76, "heightCM": 176, "dateOfBirth": "1989/07/28", "countryOfResidenceId": "GER", "linkFR": "/fr/ski-alpine-olympique/athl\u00e8tes/katharina-duerr_ath1018031tg.html", "lastName": "Duerr", "id": "1018031", "link": "/olympic-alpine-skiing/athletes/katharina-duerr_ath1018031ux.html", "noc": "GER", "events": {"ASW105000": "NONE", "ASW020000": "NONE", "ASW010000": "NONE"}, "cityOfBirth": "Munchen", "countryOfBirthId": "GER"}, {"discipline": "AS", "firstName": "Christina", "gender": "W", "age": 20, "cityOfResidence": "Oberstdorf", "weightKG": 66, "heightCM": 170, "dateOfBirth": "1990/02/06", "countryOfResidenceId": "GER", "linkFR": "/fr/ski-alpine-olympique/athl\u00e8tes/christina-geiger_ath1018013GP.html", "lastName": "Geiger", "id": "1018013", "link": "/olympic-alpine-skiing/athletes/christina-geiger_ath1018013Ms.html", "noc": "GER", "events": {"ASW020000": "NONE"}, "cityOfBirth": "Oberstdorf", "countryOfBirthId": "GER"}, {"discipline": "AS", "firstName": "Kathrin", "gender": "W", "age": 25, "cityOfResidence": "Bischofswiesen", "weightKG": 60, "heightCM": 163, "dateOfBirth": "1984/07/18", "countryOfResidenceId": "GER", "linkFR": "/fr/ski-alpine-olympique/athl\u00e8tes/kathrin-hoelzl_ath1017999gk.html", "lastName": "Hoelzl", "id": "1017999", "link": "/olympic-alpine-skiing/athletes/kathrin-hoelzl_ath1017999cp.html", "noc": "GER", "events": {"ASW020000": "NONE"}, "cityOfBirth": "Berchtesgaden", "countryOfBirthId": "GER"}, {"discipline": "AS", "firstName": "Susanne", "gender": "W", "age": 22, "cityOfResidence": "Garmisch-Partenkirchen", "weightKG": 79, "heightCM": 181, "dateOfBirth": "1987/12/08", "countryOfResidenceId": "GER", "linkFR": "/fr/ski-alpine-olympique/athl\u00e8tes/susanne-riesch_ath1018049nX.html", "lastName": "Riesch", "id": "1018049", "link": "/olympic-alpine-skiing/athletes/susanne-riesch_ath1018049jc.html", "noc": "GER", "events": {"ASW020000": "NONE"}, "cityOfBirth": "Garmisch-Partenkirchen", "countryOfBirthId": "GER"}], "noc": "GER"}, {"athletes": [{"discipline": "AS", "firstName": "Sophia", "gender": "W", "age": 21, "cityOfResidence": "Naousa", "weightKG": 61, "heightCM": 161, "dateOfBirth": "1988/03/04", "countryOfResidenceId": "GRE", "linkFR": "/fr/ski-alpine-olympique/athl\u00e8tes/sophia-ralli_ath1010903nb.html", "lastName": "Ralli", "id": "1010903", "link": "/olympic-alpine-skiing/athletes/sophia-ralli_ath1010903ZI.html", "noc": "GRE", "events": {"ASW020000": "NONE", "ASW030000": "NONE"}, "cityOfBirth": "Naousa", "countryOfBirthId": "GRE"}], "noc": "GRE"}, {"athletes": [{"discipline": "AS", "firstName": "Anna", "gender": "W", "age": 21, "cityOfResidence": "Budapest", "weightKG": 74, "heightCM": 173, "dateOfBirth": "1988/09/04", "countryOfResidenceId": "HUN", "linkFR": "/fr/ski-alpine-olympique/athl\u00e8tes/anna-berecz_ath1013079Mv.html", "lastName": "Berecz", "id": "1013079", "link": "/olympic-alpine-skiing/athletes/anna-berecz_ath1013079tQ.html", "noc": "HUN", "events": {"ASW040000": "NONE", "ASW105000": "NONE", "ASW020000": "NONE", "ASW030000": "NONE", "ASW010000": "NONE"}, "cityOfBirth": "Budapest", "countryOfBirthId": "HUN"}, {"discipline": "AS", "firstName": "Zsofia", "gender": "W", "age": 17, "cityOfResidence": "Budapest", "weightKG": 55, "heightCM": 162, "dateOfBirth": "1992/06/18", "countryOfResidenceId": "HUN", "linkFR": "/fr/ski-alpine-olympique/athl\u00e8tes/zsofia-doeme_ath1013082YG.html", "lastName": "Doeme", "id": "1013082", "link": "/olympic-alpine-skiing/athletes/zsofia-doeme_ath1013082Jn.html", "noc": "HUN", "events": {"ASW040000": "NONE", "ASW020000": "NONE", "ASW030000": "NONE"}, "cityOfBirth": "Budapest", "countryOfBirthId": "HUN"}], "noc": "HUN"}, {"athletes": [{"discipline": "AS", "firstName": "Marjan", "gender": "W", "age": 21, "cityOfResidence": "Tehran", "weightKG": 60, "heightCM": 168, "dateOfBirth": "1988/07/21", "countryOfResidenceId": "IRI", "linkFR": "/fr/ski-alpine-olympique/athl\u00e8tes/marjan-kalhor_ath1015094cf.html", "lastName": "Kalhor", "id": "1015094", "link": "/olympic-alpine-skiing/athletes/marjan-kalhor_ath1015094TY.html", "noc": "IRI", "events": {"ASW020000": "NONE", "ASW030000": "NONE"}, "cityOfBirth": "Karaj", "countryOfBirthId": "IRI"}], "noc": "IRI"}, {"athletes": [{"discipline": "AS", "firstName": "Kirsten", "gender": "W", "age": 24, "cityOfResidence": "Dublin", "weightKG": 70, "heightCM": 172, "dateOfBirth": "1985/07/25", "countryOfResidenceId": "IRL", "linkFR": "/fr/ski-alpine-olympique/athl\u00e8tes/kirsten-mcgarry_ath1013467Es.html", "lastName": "Mcgarry", "id": "1013467", "link": "/olympic-alpine-skiing/athletes/kirsten-mcgarry_ath1013467GJ.html", "noc": "IRL", "events": {"ASW040000": "NONE", "ASW105000": "NONE", "ASW020000": "NONE", "ASW030000": "NONE"}, "cityOfBirth": "Dublin", "countryOfBirthId": "IRL"}], "noc": "IRL"}, {"athletes": [{"discipline": "AS", "firstName": "Iris", "gender": "W", "age": 19, "cityOfResidence": "Kongsberg", "weightKG": 69, "heightCM": 174, "dateOfBirth": "1990/05/13", "countryOfResidenceId": "NOR", "linkFR": "/fr/ski-alpine-olympique/athl\u00e8tes/iris-gudmundsdottir_ath1018658gy.html", "lastName": "Gudmundsdottir", "id": "1018658", "link": "/olympic-alpine-skiing/athletes/iris-gudmundsdottir_ath1018658zb.html", "noc": "ISL", "events": {"ASW040000": "NONE", "ASW105000": "NONE", "ASW020000": "NONE", "ASW030000": "NONE"}, "cityOfBirth": "Akureyri", "countryOfBirthId": "ISL"}], "noc": "ISL"}, {"athletes": [{"discipline": "AS", "firstName": "Chiara", "gender": "W", "age": 25, "cityOfResidence": "Pozzo di Fassa", "weightKG": 65, "heightCM": 171, "dateOfBirth": "1984/05/06", "countryOfResidenceId": "ITA", "linkFR": "/fr/ski-alpine-olympique/athl\u00e8tes/chiara-costazza_ath1007784mL.html", "lastName": "Costazza", "id": "1007784", "link": "/olympic-alpine-skiing/athletes/chiara-costazza_ath1007784nc.html", "noc": "ITA", "events": {"ASW020000": "NONE"}, "cityOfBirth": "Cavalese", "countryOfBirthId": "ITA"}, {"discipline": "AS", "firstName": "Nicole", "gender": "W", "age": 29, "cityOfResidence": "Stelvio", "weightKG": 59, "heightCM": 159, "dateOfBirth": "1980/11/16", "countryOfResidenceId": "ITA", "linkFR": "/fr/ski-alpine-olympique/athl\u00e8tes/nicole-gius_ath1007796vF.html", "lastName": "Gius", "id": "1007796", "link": "/olympic-alpine-skiing/athletes/nicole-gius_ath1007796ba.html", "noc": "ITA", "events": {"ASW020000": "NONE", "ASW030000": "NONE"}, "cityOfBirth": "Silandro", "countryOfBirthId": "ITA"}, {"discipline": "AS", "firstName": "Denise", "gender": "W", "age": 29, "cityOfResidence": "Castelrotto", "weightKG": 60, "heightCM": 160, "dateOfBirth": "1980/08/16", "countryOfResidenceId": "ITA", "linkFR": "/fr/ski-alpine-olympique/athl\u00e8tes/denise-karbon_ath1007798qu.html", "lastName": "Karbon", "id": "1007798", "link": "/olympic-alpine-skiing/athletes/denise-karbon_ath1007798hn.html", "noc": "ITA", "events": {"ASW020000": "NONE", "ASW030000": "NONE"}, "cityOfBirth": "Bressanone", "countryOfBirthId": "ITA"}, {"discipline": "AS", "firstName": "Manuela", "gender": "W", "age": 26, "cityOfResidence": "San Vigilio di Marebbe", "weightKG": 62, "heightCM": 169, "dateOfBirth": "1983/08/28", "countryOfResidenceId": "ITA", "linkFR": "/fr/ski-alpine-olympique/athl\u00e8tes/manuela-moelgg_ath1007809uw.html", "lastName": "Moelgg", "id": "1007809", "link": "/olympic-alpine-skiing/athletes/manuela-moelgg_ath1007809rB.html", "noc": "ITA", "events": {"ASW020000": "NONE", "ASW030000": "NONE"}, "cityOfBirth": "Brunico", "countryOfBirthId": "ITA"}], "noc": "ITA"}, {"athletes": [{"discipline": "AS", "firstName": "Lyudmila", "gender": "W", "age": 23, "cityOfResidence": "Almaty", "weightKG": 56, "heightCM": 166, "dateOfBirth": "1986/04/23", "countryOfResidenceId": "KAZ", "linkFR": "/fr/ski-alpine-olympique/athl\u00e8tes/lyudmila-fedotova_ath1000410Eg.html", "lastName": "Fedotova", "id": "1000410", "link": "/olympic-alpine-skiing/athletes/lyudmila-fedotova_ath1000410QV.html", "noc": "KAZ", "events": {"ASW105000": "NONE", "ASW020000": "NONE", "ASW030000": "NONE", "ASW010000": "NONE"}, "cityOfBirth": "Almaty", "countryOfBirthId": "KAZ"}], "noc": "KAZ"}, {"athletes": [{"discipline": "AS", "firstName": "Sun Joo", "gender": "W", "age": 24, "cityOfResidence": "Seoul", "weightKG": 53, "heightCM": 156, "dateOfBirth": "1985/11/13", "countryOfResidenceId": "KOR", "linkFR": "/fr/ski-alpine-olympique/athl\u00e8tes/sun-joo-kim_ath1046763ug.html", "lastName": "Kim", "id": "1046763", "link": "/olympic-alpine-skiing/athletes/sun-joo-kim_ath1046763bB.html", "noc": "KOR", "events": {"ASW020000": "NONE", "ASW030000": "NONE"}, "cityOfBirth": "Seoul", "countryOfBirthId": "KOR"}], "noc": "KOR"}, {"athletes": [{"discipline": "AS", "firstName": "Liene", "gender": "W", "age": 21, "cityOfResidence": "Riga", "weightKG": 55, "heightCM": 156, "dateOfBirth": "1989/01/30", "countryOfResidenceId": "LAT", "linkFR": "/fr/ski-alpine-olympique/athl\u00e8tes/liene-fimbauere_ath1015299VV.html", "lastName": "Fimbauere", "id": "1015299", "link": "/olympic-alpine-skiing/athletes/liene-fimbauere_ath1015299Wm.html", "noc": "LAT", "events": {"ASW020000": "NONE", "ASW030000": "NONE"}, "cityOfBirth": "Valmiera", "countryOfBirthId": "LAT"}], "noc": "LAT"}, {"athletes": [{"discipline": "AS", "firstName": "Jacky", "gender": "W", "age": 18, "cityOfResidence": "Hazmieh", "weightKG": 56, "heightCM": 172, "dateOfBirth": "1991/10/21", "countryOfResidenceId": "LIB", "linkFR": "/fr/ski-alpine-olympique/athl\u00e8tes/jacky-chamoun_ath1015053Th.html", "lastName": "Chamoun", "id": "1015053", "link": "/olympic-alpine-skiing/athletes/jacky-chamoun_ath1015053Ka.html", "noc": "LIB", "events": {"ASW020000": "NONE", "ASW030000": "NONE"}, "cityOfBirth": "Beirut", "countryOfBirthId": "LIB"}, {"discipline": "AS", "firstName": "Chirine", "gender": "W", "age": 25, "cityOfResidence": "Beirut", "weightKG": 60, "heightCM": 168, "dateOfBirth": "1984/10/04", "countryOfResidenceId": "LIB", "linkFR": "/fr/ski-alpine-olympique/athl\u00e8tes/chirine-njeim_ath1014953dp.html", "lastName": "Njeim", "id": "1014953", "link": "/olympic-alpine-skiing/athletes/chirine-njeim_ath1014953Ui.html", "noc": "LIB", "events": {"ASW040000": "NONE", "ASW020000": "NONE", "ASW030000": "NONE"}, "cityOfBirth": "Beirut", "countryOfBirthId": "LIB"}], "noc": "LIB"}, {"athletes": [{"discipline": "AS", "firstName": "Marina", "gender": "W", "age": 25, "cityOfResidence": "Gamprin", "weightKG": 60, "heightCM": 167, "dateOfBirth": "1984/04/24", "countryOfResidenceId": "LIE", "linkFR": "/fr/ski-alpine-olympique/athl\u00e8tes/marina-nigg_ath1000102yK.html", "lastName": "Nigg", "id": "1000102", "link": "/olympic-alpine-skiing/athletes/marina-nigg_ath1000102ef.html", "noc": "LIE", "events": {"ASW020000": "NONE", "ASW030000": "NONE"}, "cityOfBirth": "Vaduz", "countryOfBirthId": "LIE"}], "noc": "LIE"}, {"athletes": [{"discipline": "AS", "firstName": "Mona", "gender": "W", "age": 18, "cityOfResidence": "Aalesund", "weightKG": 0, "heightCM": 0, "dateOfBirth": "1991/04/11", "countryOfResidenceId": "NOR", "linkFR": "/fr/ski-alpine-olympique/athl\u00e8tes/mona-loeseth_ath1006803iq.html", "lastName": "Loeseth", "id": "1006803", "link": "/olympic-alpine-skiing/athletes/mona-loeseth_ath1006803UX.html", "noc": "NOR", "events": {"ASW040000": "NONE", "ASW105000": "NONE", "ASW020000": "NONE", "ASW030000": "NONE", "ASW010000": "NONE"}, "cityOfBirth": "Aalesund", "countryOfBirthId": "NOR"}], "noc": "NOR"}, {"athletes": [{"discipline": "AS", "firstName": "Ornella", "gender": "W", "age": 18, "cityOfResidence": "Palling - 83349", "weightKG": 60, "heightCM": 168, "dateOfBirth": "1991/12/14", "countryOfResidenceId": "GER", "linkFR": "/fr/ski-alpine-olympique/athl\u00e8tes/ornella-oettl-reyes_ath1030703VV.html", "lastName": "Oettl Reyes", "id": "1030703", "link": "/olympic-alpine-skiing/athletes/ornella-oettl-reyes_ath1030703ny.html", "noc": "PER", "events": {"ASW020000": "NONE", "ASW030000": "NONE"}, "cityOfBirth": "Munchen", "countryOfBirthId": "GER"}], "noc": "PER"}, {"athletes": [{"discipline": "AS", "firstName": "Agnieszka", "gender": "W", "age": 22, "cityOfResidence": "Zakopane", "weightKG": 58, "heightCM": 159, "dateOfBirth": "1987/12/22", "countryOfResidenceId": "POL", "linkFR": "/fr/ski-alpine-olympique/athl\u00e8tes/agnieszka-gasienica-daniel_ath1002488bX.html", "lastName": "Gasienica Daniel", "id": "1002488", "link": "/olympic-alpine-skiing/athletes/agnieszka-gasienica-daniel_ath1002488iQ.html", "noc": "POL", "events": {"ASW040000": "NONE", "ASW105000": "NONE", "ASW020000": "NONE", "ASW030000": "NONE", "ASW010000": "NONE"}, "cityOfBirth": "Zakoapne", "countryOfBirthId": "POL"}], "noc": "POL"}, {"athletes": [{"discipline": "AS", "firstName": "Edith", "gender": "W", "age": 21, "cityOfResidence": "Miercurea Ciuc", "weightKG": 70, "heightCM": 163, "dateOfBirth": "1988/03/31", "countryOfResidenceId": "ROU", "linkFR": "/fr/ski-alpine-olympique/athl\u00e8tes/edith-miklos_ath1006361Vr.html", "lastName": "Miklos", "id": "1006361", "link": "/olympic-alpine-skiing/athletes/edith-miklos_ath1006361HY.html", "noc": "ROU", "events": {"ASW040000": "NONE", "ASW020000": "NONE", "ASW105000": "NONE", "ASW010000": "NONE"}, "cityOfBirth": "Miercurea Ciuc", "countryOfBirthId": "ROU"}], "noc": "ROU"}, {"athletes": [{"discipline": "AS", "firstName": "Elena", "gender": "W", "age": 19, "cityOfResidence": "Mezhdurechensk", "weightKG": 56, "heightCM": 163, "dateOfBirth": "1990/11/22", "countryOfResidenceId": "RUS", "linkFR": "/fr/ski-alpine-olympique/athl\u00e8tes/elena-prosteva_ath1001184Mp.html", "lastName": "Prosteva", "id": "1001184", "link": "/olympic-alpine-skiing/athletes/elena-prosteva_ath1001184Iu.html", "noc": "RUS", "events": {"ASW040000": "NONE", "ASW105000": "NONE", "ASW020000": "NONE", "ASW030000": "NONE", "ASW010000": "NONE"}, "cityOfBirth": "Mezhdurechensk", "countryOfBirthId": "RUS"}, {"discipline": "AS", "firstName": "Lyaysan", "gender": "W", "age": 21, "cityOfResidence": "Ufa", "weightKG": 62, "heightCM": 166, "dateOfBirth": "1989/02/01", "countryOfResidenceId": "RUS", "linkFR": "/fr/ski-alpine-olympique/athl\u00e8tes/lyaysan-rayanova_ath1001187Zx.html", "lastName": "Rayanova", "id": "1001187", "link": "/olympic-alpine-skiing/athletes/lyaysan-rayanova_ath1001187ga.html", "noc": "RUS", "events": {"ASW040000": "NONE", "ASW105000": "NONE", "ASW020000": "NONE", "ASW030000": "NONE", "ASW010000": "NONE"}, "cityOfBirth": "Ufa", "countryOfBirthId": "RUS"}], "noc": "RUS"}, {"athletes": [{"discipline": "AS", "firstName": "Ana", "gender": "W", "age": 24, "cityOfResidence": "Smartno Ob Paki", "weightKG": 61, "heightCM": 171, "dateOfBirth": "1985/08/06", "countryOfResidenceId": "SLO", "linkFR": "/fr/ski-alpine-olympique/athl\u00e8tes/ana-drev_ath1022929bf.html", "lastName": "Drev", "id": "1022929", "link": "/olympic-alpine-skiing/athletes/ana-drev_ath1022929og.html", "noc": "SLO", "events": {"ASW020000": "NONE", "ASW030000": "NONE"}, "cityOfBirth": "Slovenj Gradec", "countryOfBirthId": "SLO"}, {"discipline": "AS", "firstName": "Marusa", "gender": "W", "age": 21, "cityOfResidence": "Blejska Dobrava", "weightKG": 63, "heightCM": 167, "dateOfBirth": "1988/09/27", "countryOfResidenceId": "SLO", "linkFR": "/fr/ski-alpine-olympique/athl\u00e8tes/marusa-ferk_ath1022930jX.html", "lastName": "Ferk", "id": "1022930", "link": "/olympic-alpine-skiing/athletes/marusa-ferk_ath1022930Ps.html", "noc": "SLO", "events": {"ASW040000": "NONE", "ASW105000": "NONE", "ASW020000": "NONE", "ASW030000": "NONE", "ASW010000": "NONE"}, "cityOfBirth": "Jesenice", "countryOfBirthId": "SLO"}, {"discipline": "AS", "firstName": "Tina", "gender": "W", "age": 27, "cityOfResidence": "Crna Na Koroskem", "weightKG": 68, "heightCM": 171, "dateOfBirth": "1983/02/05", "countryOfResidenceId": "SLO", "linkFR": "/fr/ski-alpine-olympique/athl\u00e8tes/tina-maze_ath1022931gs.html", "lastName": "Maze", "id": "1022931", "link": "/olympic-alpine-skiing/athletes/tina-maze_ath1022931Cp.html", "noc": "SLO", "events": {"ASW040000": "NONE", "ASW105000": "NONE", "ASW020000": "NONE", "ASW030000": "NONE", "ASW010000": "NONE"}, "cityOfBirth": "Slovenj Gradec", "countryOfBirthId": "SLO"}], "noc": "SLO"}, {"athletes": [{"discipline": "AS", "firstName": "Nevena", "gender": "W", "age": 19, "cityOfResidence": "Kragujevac", "weightKG": 73, "heightCM": 176, "dateOfBirth": "1990/12/28", "countryOfResidenceId": "SRB", "linkFR": "/fr/ski-alpine-olympique/athl\u00e8tes/nevena-ignjatovic_ath1007778nu.html", "lastName": "Ignjatovic", "id": "1007778", "link": "/olympic-alpine-skiing/athletes/nevena-ignjatovic_ath1007778zj.html", "noc": "SRB", "events": {"ASW040000": "NONE", "ASW020000": "NONE", "ASW030000": "NONE"}, "cityOfBirth": "Kragujevac", "countryOfBirthId": "SRB"}, {"discipline": "AS", "firstName": "Jelena", "gender": "W", "age": 28, "cityOfResidence": "Belgrade", "weightKG": 62, "heightCM": 168, "dateOfBirth": "1981/07/14", "countryOfResidenceId": "SRB", "linkFR": "/fr/ski-alpine-olympique/athl\u00e8tes/jelena-lolovic_ath1007772xs.html", "lastName": "Lolovic", "id": "1007772", "link": "/olympic-alpine-skiing/athletes/jelena-lolovic_ath1007772tx.html", "noc": "SRB", "events": {"ASW040000": "NONE", "ASW020000": "NONE", "ASW030000": "NONE"}, "cityOfBirth": "Sarajevo", "countryOfBirthId": "BIH"}, {"discipline": "AS", "firstName": "Marija", "gender": "W", "age": 23, "cityOfResidence": "Uzice", "weightKG": 67, "heightCM": 173, "dateOfBirth": "1986/10/20", "countryOfResidenceId": "SRB", "linkFR": "/fr/ski-alpine-olympique/athl\u00e8tes/marija-trmcic_ath1007775Ka.html", "lastName": "Trmcic", "id": "1007775", "link": "/olympic-alpine-skiing/athletes/marija-trmcic_ath1007775BT.html", "noc": "SRB", "events": {"ASW020000": "NONE"}, "cityOfBirth": "Uzice", "countryOfBirthId": "SRB"}], "noc": "SRB"}, {"athletes": [{"discipline": "AS", "firstName": "Andrea", "gender": "W", "age": 23, "cityOfResidence": "Einsiedeln", "weightKG": 67, "heightCM": 170, "dateOfBirth": "1987/01/19", "countryOfResidenceId": "SUI", "linkFR": "/fr/ski-alpine-olympique/athl\u00e8tes/andrea-dettling_ath1009098Yi.html", "lastName": "Dettling", "id": "1009098", "link": "/olympic-alpine-skiing/athletes/andrea-dettling_ath1009098Zz.html", "noc": "SUI", "events": {"ASW040000": "NONE", "ASW105000": "NONE", "ASW020000": "NONE", "ASW030000": "NONE", "ASW010000": "NONE"}, "cityOfBirth": "Lachen", "countryOfBirthId": "SUI"}, {"discipline": "AS", "firstName": "Dominique", "gender": "W", "age": 24, "cityOfResidence": "Engelberg", "weightKG": 68, "heightCM": 172, "dateOfBirth": "1985/06/04", "countryOfResidenceId": "SUI", "linkFR": "/fr/ski-alpine-olympique/athl\u00e8tes/dominique-gisin_ath1009102DH.html", "lastName": "Gisin", "id": "1009102", "link": "/olympic-alpine-skiing/athletes/dominique-gisin_ath1009102EY.html", "noc": "SUI", "events": {"ASW105000": "NONE", "ASW020000": "NONE", "ASW030000": "NONE", "ASW010000": "NONE"}, "cityOfBirth": "Visp", "countryOfBirthId": "SUI"}, {"discipline": "AS", "firstName": "Nadja", "gender": "W", "age": 23, "cityOfResidence": "Schwyz", "weightKG": 76, "heightCM": 179, "dateOfBirth": "1986/07/23", "countryOfResidenceId": "SUI", "linkFR": "/fr/ski-alpine-olympique/athl\u00e8tes/nadja-kamer_ath1009108ki.html", "lastName": "Kamer", "id": "1009108", "link": "/olympic-alpine-skiing/athletes/nadja-kamer_ath1009108RD.html", "noc": "SUI", "events": {"ASW040000": "NONE", "ASW105000": "NONE", "ASW020000": "NONE", "ASW030000": "NONE", "ASW010000": "NONE"}, "cityOfBirth": "Schwyz", "countryOfBirthId": "SUI"}, {"discipline": "AS", "firstName": "Fabienne", "gender": "W", "age": 25, "cityOfResidence": "Sattel", "weightKG": 63, "heightCM": 167, "dateOfBirth": "1985/01/05", "countryOfResidenceId": "SUI", "linkFR": "/fr/ski-alpine-olympique/athl\u00e8tes/fabienne-suter_ath1029207mp.html", "lastName": "Suter", "id": "1029207", "link": "/olympic-alpine-skiing/athletes/fabienne-suter_ath1029207iu.html", "noc": "SUI", "events": {"ASW040000": "NONE", "ASW105000": "NONE", "ASW020000": "NONE", "ASW030000": "NONE", "ASW010000": "NONE"}, "cityOfBirth": "Schwyz", "countryOfBirthId": "SUI"}], "noc": "SUI"}, {"athletes": [{"discipline": "AS", "firstName": "Jana", "gender": "W", "age": 20, "cityOfResidence": "Kezmarok 06001", "weightKG": 65, "heightCM": 165, "dateOfBirth": "1989/07/15", "countryOfResidenceId": "SVK", "linkFR": "/fr/ski-alpine-olympique/athl\u00e8tes/jana-gantnerova_ath1030666iO.html", "lastName": "Gantnerova", "id": "1030666", "link": "/olympic-alpine-skiing/athletes/jana-gantnerova_ath1030666jf.html", "noc": "SVK", "events": {"ASW020000": "NONE", "ASW030000": "NONE"}, "cityOfBirth": "Kezmarok", "countryOfBirthId": "SVK"}, {"discipline": "AS", "firstName": "Veronika", "gender": "W", "age": 25, "cityOfResidence": "Bratislava 821 05", "weightKG": 72, "heightCM": 172, "dateOfBirth": "1984/07/15", "countryOfResidenceId": "SVK", "linkFR": "/fr/ski-alpine-olympique/athl\u00e8tes/veronika-zuzulova_ath1029542Fz.html", "lastName": "Zuzulova", "id": "1029542", "link": "/olympic-alpine-skiing/athletes/veronika-zuzulova_ath1029542Ro.html", "noc": "SVK", "events": {"ASW020000": "NONE", "ASW030000": "NONE"}, "cityOfBirth": "Bratislava", "countryOfBirthId": "SVK"}], "noc": "SVK"}, {"athletes": [{"discipline": "AS", "firstName": "Therese", "gender": "W", "age": 25, "cityOfResidence": "Johanneshov", "weightKG": 65, "heightCM": 174, "dateOfBirth": "1984/12/12", "countryOfResidenceId": "SWE", "linkFR": "/fr/ski-alpine-olympique/athl\u00e8tes/therese-borssen_ath1022465xt.html", "lastName": "Borssen", "id": "1022465", "link": "/olympic-alpine-skiing/athletes/therese-borssen_ath1022465zK.html", "noc": "SWE", "events": {"ASW020000": "NONE"}, "cityOfBirth": "Rattvik", "countryOfBirthId": "SWE"}, {"discipline": "AS", "firstName": "Frida", "gender": "W", "age": 24, "cityOfResidence": "Norberg", "weightKG": 67, "heightCM": 173, "dateOfBirth": "1985/12/13", "countryOfResidenceId": "SWE", "linkFR": "/fr/ski-alpine-olympique/athl\u00e8tes/frida-hansdotter_ath1022466Ao.html", "lastName": "Hansdotter", "id": "1022466", "link": "/olympic-alpine-skiing/athletes/frida-hansdotter_ath1022466HR.html", "noc": "SWE", "events": {"ASW020000": "NONE", "ASW030000": "NONE"}, "cityOfBirth": "Norberg", "countryOfBirthId": "SWE"}, {"discipline": "AS", "firstName": "Anja", "gender": "W", "age": 28, "cityOfResidence": "Monaco", "weightKG": 82, "heightCM": 170, "dateOfBirth": "1981/04/25", "countryOfResidenceId": "MON", "linkFR": "/fr/ski-alpine-olympique/athl\u00e8tes/anja-paerson_ath1022470pf.html", "lastName": "Paerson", "id": "1022470", "link": "/olympic-alpine-skiing/athletes/anja-paerson_ath1022470bM.html", "noc": "SWE", "events": {"ASW040000": "NONE", "ASW105000": "NONE", "ASW020000": "NONE", "ASW030000": "NONE", "ASW010000": "NONE"}, "cityOfBirth": "Tarna", "countryOfBirthId": "SWE"}, {"discipline": "AS", "firstName": "Maria", "gender": "W", "age": 23, "cityOfResidence": "Umea", "weightKG": 64, "heightCM": 170, "dateOfBirth": "1986/07/25", "countryOfResidenceId": "SWE", "linkFR": "/fr/ski-alpine-olympique/athl\u00e8tes/maria-pietilae-holmner_ath1022469JO.html", "lastName": "Pietilae-Holmner", "id": "1022469", "link": "/olympic-alpine-skiing/athletes/maria-pietilae-holmner_ath1022469vL.html", "noc": "SWE", "events": {"ASW020000": "NONE", "ASW030000": "NONE"}, "cityOfBirth": "Alidhem", "countryOfBirthId": "SWE"}], "noc": "SWE"}, {"athletes": [{"discipline": "AS", "firstName": "Tugba", "gender": "W", "age": 24, "cityOfResidence": "Kayseri", "weightKG": 63, "heightCM": 165, "dateOfBirth": "1985/05/25", "countryOfResidenceId": "TUR", "linkFR": "/fr/ski-alpine-olympique/athl\u00e8tes/tugba-dasdemir_ath1006979Ed.html", "lastName": "Dasdemir", "id": "1006979", "link": "/olympic-alpine-skiing/athletes/tugba-dasdemir_ath1006979Ai.html", "noc": "TUR", "events": {"ASW020000": "NONE", "ASW030000": "NONE"}, "cityOfBirth": "Kayseri", "countryOfBirthId": "TUR"}], "noc": "TUR"}, {"athletes": [{"discipline": "AS", "firstName": "Bogdana", "gender": "W", "age": 20, "cityOfResidence": "Kosiv", "weightKG": 65, "heightCM": 175, "dateOfBirth": "1989/08/27", "countryOfResidenceId": "UKR", "linkFR": "/fr/ski-alpine-olympique/athl\u00e8tes/bogdana-matsotska_ath1007831so.html", "lastName": "Matsotska", "id": "1007831", "link": "/olympic-alpine-skiing/athletes/bogdana-matsotska_ath1007831Ed.html", "noc": "UKR", "events": {"ASW020000": "NONE", "ASW030000": "NONE"}, "cityOfBirth": "Kosiv", "countryOfBirthId": "UKR"}, {"discipline": "AS", "firstName": "Anastasiya", "gender": "W", "age": 24, "cityOfResidence": "Uzhgorod", "weightKG": 52, "heightCM": 164, "dateOfBirth": "1985/05/10", "countryOfResidenceId": "UKR", "linkFR": "/fr/ski-alpine-olympique/athl\u00e8tes/anastasiya-skryabina_ath1007842fN.html", "lastName": "Skryabina", "id": "1007842", "link": "/olympic-alpine-skiing/athletes/anastasiya-skryabina_ath1007842Gm.html", "noc": "UKR", "events": {"ASW040000": "NONE", "ASW020000": "NONE", "ASW030000": "NONE"}, "cityOfBirth": "Lviv", "countryOfBirthId": "UKR"}], "noc": "UKR"}, {"athletes": [{"discipline": "AS", "firstName": "Hailey", "gender": "W", "age": 24, "cityOfResidence": "Boise", "weightKG": 70, "heightCM": 170, "dateOfBirth": "1985/09/17", "countryOfResidenceId": "USA", "linkFR": "/fr/ski-alpine-olympique/athl\u00e8tes/hailey-duke_ath1024062LZ.html", "lastName": "Duke", "id": "1024062", "link": "/olympic-alpine-skiing/athletes/hailey-duke_ath1024062ru.html", "noc": "USA", "events": {"ASW020000": "NONE"}, "cityOfBirth": "Sun Valley", "countryOfBirthId": "USA"}, {"discipline": "AS", "firstName": "Megan", "gender": "W", "age": 22, "cityOfResidence": "Park City", "weightKG": 59, "heightCM": 168, "dateOfBirth": "1987/09/24", "countryOfResidenceId": "USA", "linkFR": "/fr/ski-alpine-olympique/athl\u00e8tes/megan-mcjames_ath1024061on.html", "lastName": "Mcjames", "id": "1024061", "link": "/olympic-alpine-skiing/athletes/megan-mcjames_ath1024061fg.html", "noc": "USA", "events": {"ASW020000": "NONE", "ASW030000": "NONE"}, "cityOfBirth": "Salt Lake City", "countryOfBirthId": "USA"}, {"discipline": "AS", "firstName": "Sarah", "gender": "W", "age": 30, "cityOfResidence": "Edwards", "weightKG": 61, "heightCM": 163, "dateOfBirth": "1979/02/19", "countryOfResidenceId": "USA", "linkFR": "/fr/ski-alpine-olympique/athl\u00e8tes/sarah-schleper_ath1024038gY.html", "lastName": "Schleper", "id": "1024038", "link": "/olympic-alpine-skiing/athletes/sarah-schleper_ath1024038cd.html", "noc": "USA", "events": {"ASW020000": "NONE", "ASW030000": "NONE"}, "cityOfBirth": "Glenwood Springs", "countryOfBirthId": "USA"}, {"discipline": "AS", "firstName": "Lindsey", "gender": "W", "age": 25, "cityOfResidence": "West Wendover", "weightKG": 75, "heightCM": 178, "dateOfBirth": "1984/10/18", "countryOfResidenceId": "USA", "linkFR": "/fr/ski-alpine-olympique/athl\u00e8tes/lindsey-vonn_ath1024072dW.html", "lastName": "Vonn", "id": "1024072", "link": "/olympic-alpine-skiing/athletes/lindsey-vonn_ath1024072PD.html", "noc": "USA", "events": {"ASW040000": "NONE", "ASW105000": "NONE", "ASW020000": "NONE", "ASW030000": "NONE", "ASW010000": "NONE"}, "cityOfBirth": "Minneapolis", "countryOfBirthId": "USA"}], "noc": "USA"}, {"athletes": [{"discipline": "AS", "firstName": "Kseniya", "gender": "W", "age": 22, "cityOfResidence": "Tashkent", "weightKG": 60, "heightCM": 180, "dateOfBirth": "1987/11/25", "countryOfResidenceId": "UZB", "linkFR": "/fr/ski-alpine-olympique/athl\u00e8tes/kseniya-grigoreva_ath1033102Gd.html", "lastName": "Grigoreva", "id": "1033102", "link": "/olympic-alpine-skiing/athletes/kseniya-grigoreva_ath1033102SS.html", "noc": "UZB", "events": {"ASW020000": "NONE", "ASW030000": "NONE"}, "cityOfBirth": "Tashkent", "countryOfBirthId": "UZB"}], "noc": "UZB"}]}